CHANGES.rst
CONTRIBUTORS.rst
MANIFEST.in
README.rst
setup.cfg
setup.py
docs/LICENSE.GPL
docs/LICENSE.txt
src/covertile/__init__.py
src/covertile.cycle2.egg-info/PKG-INFO
src/covertile.cycle2.egg-info/SOURCES.txt
src/covertile.cycle2.egg-info/dependency_links.txt
src/covertile.cycle2.egg-info/entry_points.txt
src/covertile.cycle2.egg-info/namespace_packages.txt
src/covertile.cycle2.egg-info/not-zip-safe
src/covertile.cycle2.egg-info/requires.txt
src/covertile.cycle2.egg-info/top_level.txt
src/covertile/cycle2/__init__.py
src/covertile/cycle2/config.py
src/covertile/cycle2/configure.zcml
src/covertile/cycle2/interfaces.py
src/covertile/cycle2/profiles.zcml
src/covertile/cycle2/testing.py
src/covertile/cycle2/Extensions/Install.py
src/covertile/cycle2/Extensions/__init__.py
src/covertile/cycle2/locales/covertile.cycle2.pot
src/covertile/cycle2/locales/manual.pot
src/covertile/cycle2/locales/update-i18n.sh
src/covertile/cycle2/locales/en/LC_MESSAGES/covertile.cycle2.mo
src/covertile/cycle2/locales/en/LC_MESSAGES/covertile.cycle2.po
src/covertile/cycle2/locales/nl/LC_MESSAGES/covertile.cycle2.mo
src/covertile/cycle2/locales/nl/LC_MESSAGES/covertile.cycle2.po
src/covertile/cycle2/profiles/default/browserlayer.xml
src/covertile/cycle2/profiles/default/cssregistry.xml
src/covertile/cycle2/profiles/default/jsregistry.xml
src/covertile/cycle2/profiles/default/metadata.xml
src/covertile/cycle2/profiles/default/registry.xml
src/covertile/cycle2/profiles/uninstall/collective.tile.cycle2.txt
src/covertile/cycle2/static/cycle2.cover_theme.css
src/covertile/cycle2/static/dot.png
src/covertile/cycle2/static/next-arrow.png
src/covertile/cycle2/static/prev-arrow.png
src/covertile/cycle2/tests/__init__.py
src/covertile/cycle2/tests/test_carousel_tile.py
src/covertile/cycle2/tests/test_carousel_tile.robot
src/covertile/cycle2/tests/test_robot.py
src/covertile/cycle2/tests/test_setup.py
src/covertile/cycle2/tiles/__init__.py
src/covertile/cycle2/tiles/carousel.py
src/covertile/cycle2/tiles/configure.zcml
src/covertile/cycle2/tiles/tiles.zcml
src/covertile/cycle2/tiles/configuration_widgets/__init__.py
src/covertile/cycle2/tiles/configuration_widgets/configure.zcml
src/covertile/cycle2/tiles/configuration_widgets/overlaytextarea.pt
src/covertile/cycle2/tiles/configuration_widgets/overlaytextarea.py
