Metadata-Version: 2.1
Name: covertile.cycle2
Version: 1.0.0
Summary: A carousel tile for collective.cover based on the Cycle2 slideshow plugin for jQuery.
Home-page: https://github.com/collective/covertile.cycle2
Author: Simples Consultoria
Author-email: produts@simplesconsultoria.com.br
License: UNKNOWN
Keywords: plone tile cycle2 slideshow carousel
Platform: UNKNOWN
Classifier: Development Status :: 4 - Beta
Classifier: Environment :: Web Environment
Classifier: Framework :: Plone
Classifier: Framework :: Plone :: 4.3
Classifier: Intended Audience :: End Users/Desktop
Classifier: Intended Audience :: System Administrators
Classifier: License :: OSI Approved :: GNU General Public License v2 (GPLv2)
Classifier: Operating System :: OS Independent
Classifier: Programming Language :: JavaScript
Classifier: Programming Language :: Python
Classifier: Programming Language :: Python :: 2.7
Classifier: Topic :: Software Development :: Libraries :: Python Modules
Provides-Extra: test
